<tool id="pm_uep_opt_write" name="Generate uep outputs (pm-uep-opt)" version="0.1.0" python_template_version="3.5">
    <requirements>
        <requirement type="package">pymuon-suite</requirement>
    </requirements>
    <command detect_errors="exit_code"><![CDATA[
        pip show pymuon-suite || ( git clone https://github.com/muon-spectroscopy-computational-project/pymuon-suite /tmp/pymuon-suite && pip install /tmp/pymuon-suite && rm -rf /tmp/pymuon-suite) &&
        unzip $folder &&
        if test -f "params.yaml"; then echo "params.yaml present"; else echo "params.yaml missing" && exit 64; fi 
        && if test -f "input.cell"; then echo "input.cell present"; else echo "input.cell missing" && exit 64; fi 
        && cp $charge_density $charge_density.name &&
        cp $castep_log $castep_log.name &&
        out_folder="`python ${__tool_directory__}/get_out_folder.py`" &&
        find \$out_folder -type f -name "*.yaml" | xargs sed -i "s#^chden_path: .*#chden_path: .\/#g" &&
        bash ${__tool_directory__}/run.sh \$out_folder &&
        zip -r out_zip.zip \$out_folder params.yaml input.cell &&
        find \$out_folder > tree.txt
    ]]></command>
    <inputs>
        <param type="data" name="folder" format="zip" />
        <param type="data" name="charge_density" format="den_fmt" />
        <param type="data" name="castep_log" format="castep" />
    </inputs>
    <outputs>
        <data label="UEP output for $folder.name" name="out_zip" format="zip" from_work_dir="out_zip.zip"/>
        <data label="file tree for testing" name="file_tree" format="txt" from_work_dir="tree.txt" hidden="true"/>
    </outputs>
    <tests>
        <test>
            <param name="folder" value="muonated.zip" ftype='zip'/>
            <param name="charge_density" value="Si.den_fmt" ftype="txt"/>
            <param name="castep_log" value="Si.castep" ftype="txt"/>
            <output name="file_tree" file="tree.txt" ftype="txt" compare="sim_size" delta="1"/>
        </test>
        <test>
            <param name="folder" value="muonated-default-folder.zip" ftype='zip'/>
            <param name="charge_density" value="Si.den_fmt" ftype="txt"/>
            <param name="castep_log" value="Si.castep" ftype="txt"/>
            <output name="file_tree" file="tree-default-folder.txt" ftype="txt" compare="sim_size" delta="1"/>
        </test>
        
    </tests>
    <help><![CDATA[
        usage: pm-uep-opt [-h] [-t {r,w}] structures parameter_file

        Given some input muonated structures, applies UEP optimization to refine them.
    ]]></help>
    <citations>
        <citation type="bibtex">
@misc{github,
  author = {Muon Spectroscopy Computational Project},
  year = {2021},
  title = {pymuon-suite},
  publisher = {GitHub},
  journal = {GitHub repository},
  url = {https://github.com/muon-spectroscopy-computational-project/pymuon-suite/},
}</citation>
    </citations>
</tool>
